LICENSE
MANIFEST.in
README.rst
requirements.txt
setup.py
gogame/__init__.py
gogame/board.py
gogame/enum.py
gogame/player.py
gogame/territory.py
gogame.egg-info/PKG-INFO
gogame.egg-info/SOURCES.txt
gogame.egg-info/dependency_links.txt
gogame.egg-info/requires.txt
gogame.egg-info/top_level.txt