Metadata-Version: 2.1
Name: gogame
Version: 0.0.2
Summary: An easy way to simulate and automize go-like programs.
Home-page: https://github.com/BlackRaven0405/gogame
Author: BlackRaven0405
Author-email: ljouhault@crowbots.shop
License: MIT
Keywords: go gogame
Platform: UNKNOWN
Requires-Python: >=3.8
